<?xml version="1.0" encoding="UTF-8"?>
<!-- All quantities are in Hartree atomic units unless otherwise specified -->
<qes:espresso xmlns:xsi="http://www.w3.org/2001/XMLSchema-instance" xmlns:qes="http://www.quantum-espresso.org/ns/qes/qes-1.0" xsi:schemaLocation="http://www.quantum-espresso.org/ns/qes/qes-1.0 http://www.quantum-espresso.org/ns/qes/qes_230310.xsd" Units="Hartree atomic units">
  <general_info>
    <xml_format NAME="QEXSD" VERSION="23.03.10">QEXSD_23.03.10</xml_format>
    <creator NAME="PWSCF" VERSION="7.3">XML file generated by PWSCF</creator>
    <created DATE="15Dec2024" TIME="21:52:13">This run was terminated on:  21:52:13  15 Dec 2024</created>
    <job></job>
  </general_info>
  <parallel_info>
    <nprocs>1</nprocs>
    <nthreads>1</nthreads>
    <ntasks>1</ntasks>
    <nbgrp>1</nbgrp>
    <npool>1</npool>
    <ndiag>1</ndiag>
  </parallel_info>
  <input>
    <control_variables>
      <title></title>
      <calculation>vc-relax</calculation>
      <restart_mode>from_scratch</restart_mode>
      <prefix>vcrelax</prefix>
      <pseudo_dir>./PSEUDO</pseudo_dir>
      <outdir>./tmp</outdir>
      <stress>true</stress>
      <forces>true</forces>
      <wf_collect>true</wf_collect>
      <disk_io>low</disk_io>
      <max_seconds>10000000</max_seconds>
      <nstep>50</nstep>
      <etot_conv_thr>5.000000000000000E-005</etot_conv_thr>
      <forc_conv_thr>5.000000000000000E-004</forc_conv_thr>
      <press_conv_thr>5.000000000000000E-001</press_conv_thr>
      <verbosity>low</verbosity>
      <print_every>100000</print_every>
      <fcp>false</fcp>
      <rism>false</rism>
    </control_variables>
    <atomic_species ntyp="1">
      <species name="Si">
        <mass>2.876000000000000E+001</mass>
        <pseudo_file>Si.LDA.upf</pseudo_file>
      </species>
    </atomic_species>
    <atomic_structure nat="2" alat="10.210000000000001" bravais_index="2">
      <atomic_positions>
        <atom name="Si" index="1">
  0.000000000000000E+000  0.000000000000000E+000  0.000000000000000E+000
        </atom>
        <atom name="Si" index="2">2.552500000000000E+000  2.552500000000000E+000  2.552500000000000E+000</atom>
      </atomic_positions>
      <cell>
        <a1>-5.105000000000000E+000  0.000000000000000E+000  5.105000000000000E+000</a1>
        <a2>0.000000000000000E+000  5.105000000000000E+000  5.105000000000000E+000</a2>
        <a3>-5.105000000000000E+000  5.105000000000000E+000  0.000000000000000E+000</a3>
      </cell>
    </atomic_structure>
    <dft>
      <functional>PW</functional>
    </dft>
    <spin>
      <lsda>false</lsda>
      <noncolin>false</noncolin>
      <spinorbit>false</spinorbit>
    </spin>
    <bands>
      <tot_charge>0.000000000000000E+000</tot_charge>
      <occupations>tetrahedra_opt</occupations>
    </bands>
    <basis>
      <gamma_only>false</gamma_only>
      <ecutwfc>3.000000000000000E+001</ecutwfc>
      <ecutrho>1.200000000000000E+002</ecutrho>
    </basis>
    <electron_control>
      <diagonalization>davidson</diagonalization>
      <mixing_mode>plain</mixing_mode>
      <mixing_beta>7.000000000000000E-001</mixing_beta>
      <conv_thr>5.000000000000000E-007</conv_thr>
      <mixing_ndim>8</mixing_ndim>
      <max_nstep>100</max_nstep>
      <exx_nstep>100</exx_nstep>
      <real_space_q>false</real_space_q>
      <real_space_beta>false</real_space_beta>
      <tq_smoothing>false</tq_smoothing>
      <tbeta_smoothing>false</tbeta_smoothing>
      <diago_thr_init>0.000000000000000E+000</diago_thr_init>
      <diago_full_acc>false</diago_full_acc>
      <diago_cg_maxiter>20</diago_cg_maxiter>
      <diago_ppcg_maxiter>20</diago_ppcg_maxiter>
      <diago_rmm_ndim>4</diago_rmm_ndim>
      <diago_gs_nblock>16</diago_gs_nblock>
      <diago_rmm_conv>false</diago_rmm_conv>
    </electron_control>
    <k_points_IBZ>
      <monkhorst_pack nk1="6" nk2="6" nk3="6" k1="0" k2="0" k3="0">Monkhorst-Pack</monkhorst_pack>
    </k_points_IBZ>
    <ion_control>
      <ion_dynamics>bfgs</ion_dynamics>
      <upscale>1.000000000000000E+002</upscale>
      <remove_rigid_rot>false</remove_rigid_rot>
      <refold_pos>false</refold_pos>
      <bfgs>
        <ndim>1</ndim>
        <trust_radius_min>1.000000000000000E-004</trust_radius_min>
        <trust_radius_max>8.000000000000000E-001</trust_radius_max>
        <trust_radius_init>1.000000000000000E-001</trust_radius_init>
        <w1>1.000000000000000E-002</w1>
        <w2>5.000000000000000E-001</w2>
      </bfgs>
    </ion_control>
    <cell_control>
      <cell_dynamics>bfgs</cell_dynamics>
      <pressure>0.000000000000000E+000</pressure>
      <wmass>0.000000000000000E+000</wmass>
      <cell_do_free>all</cell_do_free>
    </cell_control>
    <symmetry_flags>
      <nosym>false</nosym>
      <nosym_evc>false</nosym_evc>
      <noinv>false</noinv>
      <no_t_rev>false</no_t_rev>
      <force_symmorphic>false</force_symmorphic>
      <use_all_frac>false</use_all_frac>
    </symmetry_flags>
    <free_positions rank="2" dims="           3           2">
           1           1           1
           1           1           1
    </free_positions>
  </input>
  <step>
    <scf_conv>
      <convergence_achieved>true</convergence_achieved>
      <n_scf_steps>4</n_scf_steps>
      <scf_error>7.849169246492177E-008</scf_error>
    </scf_conv>
    <atomic_structure nat="2" alat="10.210000000000001">
      <atomic_positions>
        <atom name="Si" index="1">
  0.000000000000000E+000  0.000000000000000E+000  0.000000000000000E+000
        </atom>
        <atom name="Si" index="2">2.552500000000000E+000  2.552500000000000E+000  2.552500000000000E+000</atom>
      </atomic_positions>
      <cell>
        <a1>-5.105000000000000E+000  0.000000000000000E+000  5.105000000000000E+000</a1>
        <a2>0.000000000000000E+000  5.105000000000000E+000  5.105000000000000E+000</a2>
        <a3>-5.105000000000000E+000  5.105000000000000E+000  0.000000000000000E+000</a3>
      </cell>
    </atomic_structure>
    <total_energy>
      <etot>-8.524484342038306E+000</etot>
      <eband>3.204652154227832E-001</eband>
      <ehart>5.432974553662606E-001</ehart>
      <vtxc>-3.248748722565988E+000</vtxc>
      <etxc>-3.108636496754674E+000</etxc>
      <ewald>-8.441603205208107E+000</ewald>
    </total_energy>
    <forces rank="2" dims="           3           2">
  0.000000000000000E+000  0.000000000000000E+000  0.000000000000000E+000
  0.000000000000000E+000  0.000000000000000E+000  0.000000000000000E+000
    </forces>
    <stress rank="2" dims="           3           3">
 -1.375692069685893E-005 -2.541098841762901E-021 -4.235164736271502E-021
 -2.541098841762901E-021 -1.375692069685894E-005  5.929230630780102E-021
 -5.082197683525802E-021  5.082197683525802E-021 -1.375692069685893E-005
    </stress>
  </step>
  <step>
    <scf_conv>
      <convergence_achieved>true</convergence_achieved>
      <n_scf_steps>1</n_scf_steps>
      <scf_error>2.262042840421312E-007</scf_error>
    </scf_conv>
    <atomic_structure nat="2" alat="10.210000000000001">
      <atomic_positions>
        <atom name="Si" index="1">
 -0.000000000000000E+000  0.000000000000000E+000  0.000000000000000E+000
        </atom>
        <atom name="Si" index="2">2.550744272996063E+000  2.550744272996064E+000  2.550744272996064E+000</atom>
      </atomic_positions>
      <cell>
        <a1>-5.101488545992127E+000  1.301042606982605E-018  5.101488545992127E+000</a1>
        <a2>-1.517883041479706E-018  5.101488545992127E+000  5.101488545992127E+000</a2>
        <a3>-5.101488545992127E+000  5.101488545992127E+000  3.035766082959412E-018</a3>
      </cell>
    </atomic_structure>
    <total_energy>
      <etot>-8.524489978279036E+000</etot>
      <eband>3.246511038901731E-001</eband>
      <ehart>5.426019530086401E-001</ehart>
      <vtxc>-3.250345440889026E+000</vtxc>
      <etxc>-3.109914163650255E+000</etxc>
      <ewald>-8.447413725188479E+000</ewald>
    </total_energy>
    <forces rank="2" dims="           3           2">
 -2.055739306143453E-033  2.055739306143453E-033 -2.055739306143453E-033
 -5.139348265358634E-033 -9.250826877645539E-033 -5.139348265358634E-033
    </forces>
    <stress rank="2" dims="           3           3">
 -5.905609670674688E-006  8.470329472543003E-022 -2.541098841762901E-021
  0.000000000000000E+000 -5.905609670674685E-006 -8.470329472543003E-022
 -2.541098841762901E-021  0.000000000000000E+000 -5.905609670674684E-006
    </stress>
  </step>
  <step>
    <scf_conv>
      <convergence_achieved>true</convergence_achieved>
      <n_scf_steps>2</n_scf_steps>
      <scf_error>9.044729306218286E-010</scf_error>
    </scf_conv>
    <atomic_structure nat="2" alat="10.210000000000001">
      <atomic_positions>
        <atom name="Si" index="1">
 -7.183003021871650E-033  7.183003021871651E-033 -7.183003021871653E-033
        </atom>
        <atom name="Si" index="2">2.549426826834024E+000  2.549426826834025E+000  2.549426826834025E+000</atom>
      </atomic_positions>
      <cell>
        <a1>-5.098853653668050E+000  2.709701528279373E-019  5.098853653668050E+000</a1>
        <a2>-2.602245994552088E-018  5.098853653668050E+000  5.098853653668050E+000</a2>
        <a3>-5.098853653668050E+000  5.098853653668050E+000  4.336808689942018E-018</a3>
      </cell>
    </atomic_structure>
    <total_energy>
      <etot>-8.524491693986471E+000</etot>
      <eband>3.284475010585485E-001</eband>
      <ehart>5.418212553483557E-001</ehart>
      <vtxc>-3.251408897643434E+000</vtxc>
      <etxc>-3.110757164812016E+000</etxc>
      <ewald>-8.451779025093533E+000</ewald>
    </total_energy>
    <forces rank="2" dims="           3           2">
  0.000000000000000E+000  0.000000000000000E+000  0.000000000000000E+000
  0.000000000000000E+000  0.000000000000000E+000  0.000000000000000E+000
    </forces>
    <stress rank="2" dims="           3           3">
 -1.581535934035499E-006 -4.235164736271502E-022 -8.470329472543003E-022
 -4.235164736271502E-022 -1.581535934035499E-006  0.000000000000000E+000
 -8.470329472543003E-022  0.000000000000000E+000 -1.581535934035499E-006
    </stress>
  </step>
  <output>
    <convergence_info>
      <scf_conv>
        <convergence_achieved>true</convergence_achieved>
        <n_scf_steps>6</n_scf_steps>
        <scf_error>6.793456877637204E-010</scf_error>
      </scf_conv>
      <opt_conv>
        <convergence_achieved>true</convergence_achieved>
        <n_opt_steps>2</n_opt_steps>
        <grad_norm>0.000000000000000E+000</grad_norm>
      </opt_conv>
    </convergence_info>
    <algorithmic_info>
      <real_space_q>false</real_space_q>
      <real_space_beta>false</real_space_beta>
      <uspp>false</uspp>
      <paw>false</paw>
    </algorithmic_info>
    <atomic_species ntyp="1" pseudo_dir="./PSEUDO/">
      <species name="Si">
        <mass>2.876000000000000E+001</mass>
        <pseudo_file>Si.LDA.upf</pseudo_file>
      </species>
    </atomic_species>
    <atomic_structure nat="2" alat="10.210000000000001" bravais_index="2">
      <atomic_positions>
        <atom name="Si" index="1">
 -7.183003021871650E-033  7.183003021871651E-033 -7.183003021871654E-033
        </atom>
        <atom name="Si" index="2">2.549426826834024E+000  2.549426826834025E+000  2.549426826834025E+000</atom>
      </atomic_positions>
      <cell>
        <a1>-5.098853653668050E+000  2.709701528279373E-019  5.098853653668050E+000</a1>
        <a2>-2.602245994552088E-018  5.098853653668050E+000  5.098853653668050E+000</a2>
        <a3>-5.098853653668050E+000  5.098853653668050E+000  4.336808689942018E-018</a3>
      </cell>
    </atomic_structure>
    <symmetries>
      <nsym>48</nsym>
      <nrot>48</nrot>
      <space_group>0</space_group>
      <symmetry>
        <info name="identity">crystal_symmetry</info>
        <rotation rank="2" dims="           3           3">
  1.000000000000000E+000  0.000000000000000E+000  0.000000000000000E+000
  0.000000000000000E+000  1.000000000000000E+000  0.000000000000000E+000
  0.000000000000000E+000  0.000000000000000E+000  1.000000000000000E+000
        </rotation>
        <fractional_translation>
  0.000000000000000E+000  0.000000000000000E+000  0.000000000000000E+000
        </fractional_translation>
        <equivalent_atoms size="2" nat="2">
           1           2
        </equivalent_atoms>
      </symmetry>
      <symmetry>
        <info name="180 deg rotation - cart. axis [0,0,1]">crystal_symmetry</info>
        <rotation rank="2" dims="           3           3">
  0.000000000000000E+000  1.000000000000000E+000  0.000000000000000E+000
  1.000000000000000E+000  0.000000000000000E+000  0.000000000000000E+000
 -1.000000000000000E+000 -1.000000000000000E+000 -1.000000000000000E+000
        </rotation>
        <fractional_translation>
  0.000000000000000E+000  0.000000000000000E+000  0.000000000000000E+000
        </fractional_translation>
        <equivalent_atoms size="2" nat="2">
           1           2
        </equivalent_atoms>
      </symmetry>
      <symmetry>
        <info name="180 deg rotation - cart. axis [0,1,0]">crystal_symmetry</info>
        <rotation rank="2" dims="           3           3">
 -1.000000000000000E+000 -1.000000000000000E+000 -1.000000000000000E+000
  0.000000000000000E+000  0.000000000000000E+000  1.000000000000000E+000
  0.000000000000000E+000  1.000000000000000E+000  0.000000000000000E+000
        </rotation>
        <fractional_translation>
  0.000000000000000E+000  0.000000000000000E+000  0.000000000000000E+000
        </fractional_translation>
        <equivalent_atoms size="2" nat="2">
           1           2
        </equivalent_atoms>
      </symmetry>
      <symmetry>
        <info name="180 deg rotation - cart. axis [1,0,0]">crystal_symmetry</info>
        <rotation rank="2" dims="           3           3">
  0.000000000000000E+000  0.000000000000000E+000  1.000000000000000E+000
 -1.000000000000000E+000 -1.000000000000000E+000 -1.000000000000000E+000
  1.000000000000000E+000  0.000000000000000E+000  0.000000000000000E+000
        </rotation>
        <fractional_translation>
  0.000000000000000E+000  0.000000000000000E+000  0.000000000000000E+000
        </fractional_translation>
        <equivalent_atoms size="2" nat="2">
           1           2
        </equivalent_atoms>
      </symmetry>
      <symmetry>
        <info name="180 deg rotation - cart. axis [1,1,0]">crystal_symmetry</info>
        <rotation rank="2" dims="           3           3">
  0.000000000000000E+000 -1.000000000000000E+000  0.000000000000000E+000
 -1.000000000000000E+000  0.000000000000000E+000  0.000000000000000E+000
  0.000000000000000E+000  0.000000000000000E+000 -1.000000000000000E+000
        </rotation>
        <fractional_translation>
  2.500000000000000E-001  2.500000000000000E-001  2.500000000000000E-001
        </fractional_translation>
        <equivalent_atoms size="2" nat="2">
           2           1
        </equivalent_atoms>
      </symmetry>
      <symmetry>
        <info name="180 deg rotation - cart. axis [1,-1,0]">crystal_symmetry</info>
        <rotation rank="2" dims="           3           3">
 -1.000000000000000E+000  0.000000000000000E+000  0.000000000000000E+000
  0.000000000000000E+000 -1.000000000000000E+000  0.000000000000000E+000
  1.000000000000000E+000  1.000000000000000E+000  1.000000000000000E+000
        </rotation>
        <fractional_translation>
  2.500000000000000E-001  2.500000000000000E-001  2.500000000000000E-001
        </fractional_translation>
        <equivalent_atoms size="2" nat="2">
           2           1
        </equivalent_atoms>
      </symmetry>
      <symmetry>
        <info name=" 90 deg rotation - cart. axis [0,0,-1]">crystal_symmetry</info>
        <rotation rank="2" dims="           3           3">
  0.000000000000000E+000  0.000000000000000E+000 -1.000000000000000E+000
  1.000000000000000E+000  1.000000000000000E+000  1.000000000000000E+000
  0.000000000000000E+000 -1.000000000000000E+000  0.000000000000000E+000
        </rotation>
        <fractional_translation>
  2.500000000000000E-001  2.500000000000000E-001  2.500000000000000E-001
        </fractional_translation>
        <equivalent_atoms size="2" nat="2">
           2           1
        </equivalent_atoms>
      </symmetry>
      <symmetry>
        <info name=" 90 deg rotation - cart. axis [0,0,1]">crystal_symmetry</info>
        <rotation rank="2" dims="           3           3">
  1.000000000000000E+000  1.000000000000000E+000  1.000000000000000E+000
  0.000000000000000E+000  0.000000000000000E+000 -1.000000000000000E+000
 -1.000000000000000E+000  0.000000000000000E+000  0.000000000000000E+000
        </rotation>
        <fractional_translation>
  2.500000000000000E-001  2.500000000000000E-001  2.500000000000000E-001
        </fractional_translation>
        <equivalent_atoms size="2" nat="2">
           2           1
        </equivalent_atoms>
      </symmetry>
      <symmetry>
        <info name="180 deg rotation - cart. axis [1,0,1]">crystal_symmetry</info>
        <rotation rank="2" dims="           3           3">
 -1.000000000000000E+000  0.000000000000000E+000  0.000000000000000E+000
  0.000000000000000E+000  0.000000000000000E+000 -1.000000000000000E+000
  0.000000000000000E+000 -1.000000000000000E+000  0.000000000000000E+000
        </rotation>
        <fractional_translation>
  2.500000000000000E-001  2.500000000000000E-001  2.500000000000000E-001
        </fractional_translation>
        <equivalent_atoms size="2" nat="2">
           2           1
        </equivalent_atoms>
      </symmetry>
      <symmetry>
        <info name="180 deg rotation - cart. axis [-1,0,1]">crystal_symmetry</info>
        <rotation rank="2" dims="           3           3">
  1.000000000000000E+000  1.000000000000000E+000  1.000000000000000E+000
  0.000000000000000E+000 -1.000000000000000E+000  0.000000000000000E+000
  0.000000000000000E+000  0.000000000000000E+000 -1.000000000000000E+000
        </rotation>
        <fractional_translation>
  2.500000000000000E-001  2.500000000000000E-001  2.500000000000000E-001
        </fractional_translation>
        <equivalent_atoms size="2" nat="2">
           2           1
        </equivalent_atoms>
      </symmetry>
      <symmetry>
        <info name=" 90 deg rotation - cart. axis [0,1,0]">crystal_symmetry</info>
        <rotation rank="2" dims="           3           3">
  0.000000000000000E+000 -1.000000000000000E+000  0.000000000000000E+000
  1.000000000000000E+000  1.000000000000000E+000  1.000000000000000E+000
 -1.000000000000000E+000  0.000000000000000E+000  0.000000000000000E+000
        </rotation>
        <fractional_translation>
  2.500000000000000E-001  2.500000000000000E-001  2.500000000000000E-001
        </fractional_translation>
        <equivalent_atoms size="2" nat="2">
           2           1
        </equivalent_atoms>
      </symmetry>
      <symmetry>
        <info name=" 90 deg rotation - cart. axis [0,-1,0]">crystal_symmetry</info>
        <rotation rank="2" dims="           3           3">
  0.000000000000000E+000  0.000000000000000E+000 -1.000000000000000E+000
 -1.000000000000000E+000  0.000000000000000E+000  0.000000000000000E+000
  1.000000000000000E+000  1.000000000000000E+000  1.000000000000000E+000
        </rotation>
        <fractional_translation>
  2.500000000000000E-001  2.500000000000000E-001  2.500000000000000E-001
        </fractional_translation>
        <equivalent_atoms size="2" nat="2">
           2           1
        </equivalent_atoms>
      </symmetry>
      <symmetry>
        <info name="180 deg rotation - cart. axis [0,1,1]">crystal_symmetry</info>
        <rotation rank="2" dims="           3           3">
 -1.000000000000000E+000  0.000000000000000E+000  0.000000000000000E+000
  1.000000000000000E+000  1.000000000000000E+000  1.000000000000000E+000
  0.000000000000000E+000  0.000000000000000E+000 -1.000000000000000E+000
        </rotation>
        <fractional_translation>
  2.500000000000000E-001  2.500000000000000E-001  2.500000000000000E-001
        </fractional_translation>
        <equivalent_atoms size="2" nat="2">
           2           1
        </equivalent_atoms>
      </symmetry>
      <symmetry>
        <info name="180 deg rotation - cart. axis [0,1,-1]">crystal_symmetry</info>
        <rotation rank="2" dims="           3           3">
  0.000000000000000E+000  0.000000000000000E+000 -1.000000000000000E+000
  0.000000000000000E+000 -1.000000000000000E+000  0.000000000000000E+000
 -1.000000000000000E+000  0.000000000000000E+000  0.000000000000000E+000
        </rotation>
        <fractional_translation>
  2.500000000000000E-001  2.500000000000000E-001  2.500000000000000E-001
        </fractional_translation>
        <equivalent_atoms size="2" nat="2">
           2           1
        </equivalent_atoms>
      </symmetry>
      <symmetry>
        <info name=" 90 deg rotation - cart. axis [-1,0,0]">crystal_symmetry</info>
        <rotation rank="2" dims="           3           3">
  0.000000000000000E+000 -1.000000000000000E+000  0.000000000000000E+000
  0.000000000000000E+000  0.000000000000000E+000 -1.000000000000000E+000
  1.000000000000000E+000  1.000000000000000E+000  1.000000000000000E+000
        </rotation>
        <fractional_translation>
  2.500000000000000E-001  2.500000000000000E-001  2.500000000000000E-001
        </fractional_translation>
        <equivalent_atoms size="2" nat="2">
           2           1
        </equivalent_atoms>
      </symmetry>
      <symmetry>
        <info name=" 90 deg rotation - cart. axis [1,0,0]">crystal_symmetry</info>
        <rotation rank="2" dims="           3           3">
  1.000000000000000E+000  1.000000000000000E+000  1.000000000000000E+000
 -1.000000000000000E+000  0.000000000000000E+000  0.000000000000000E+000
  0.000000000000000E+000 -1.000000000000000E+000  0.000000000000000E+000
        </rotation>
        <fractional_translation>
  2.500000000000000E-001  2.500000000000000E-001  2.500000000000000E-001
        </fractional_translation>
        <equivalent_atoms size="2" nat="2">
           2           1
        </equivalent_atoms>
      </symmetry>
      <symmetry>
        <info name="120 deg rotation - cart. axis [-1,-1,-1]">crystal_symmetry</info>
        <rotation rank="2" dims="           3           3">
 -1.000000000000000E+000 -1.000000000000000E+000 -1.000000000000000E+000
  0.000000000000000E+000  1.000000000000000E+000  0.000000000000000E+000
  1.000000000000000E+000  0.000000000000000E+000  0.000000000000000E+000
        </rotation>
        <fractional_translation>
  0.000000000000000E+000  0.000000000000000E+000  0.000000000000000E+000
        </fractional_translation>
        <equivalent_atoms size="2" nat="2">
           1           2
        </equivalent_atoms>
      </symmetry>
      <symmetry>
        <info name="120 deg rotation - cart. axis [-1,1,1]">crystal_symmetry</info>
        <rotation rank="2" dims="           3           3">
  0.000000000000000E+000  0.000000000000000E+000  1.000000000000000E+000
  1.000000000000000E+000  0.000000000000000E+000  0.000000000000000E+000
  0.000000000000000E+000  1.000000000000000E+000  0.000000000000000E+000
        </rotation>
        <fractional_translation>
  0.000000000000000E+000  0.000000000000000E+000  0.000000000000000E+000
        </fractional_translation>
        <equivalent_atoms size="2" nat="2">
           1           2
        </equivalent_atoms>
      </symmetry>
      <symmetry>
        <info name="120 deg rotation - cart. axis [1,1,-1]">crystal_symmetry</info>
        <rotation rank="2" dims="           3           3">
  1.000000000000000E+000  0.000000000000000E+000  0.000000000000000E+000
  0.000000000000000E+000  0.000000000000000E+000  1.000000000000000E+000
 -1.000000000000000E+000 -1.000000000000000E+000 -1.000000000000000E+000
        </rotation>
        <fractional_translation>
  0.000000000000000E+000  0.000000000000000E+000  0.000000000000000E+000
        </fractional_translation>
        <equivalent_atoms size="2" nat="2">
           1           2
        </equivalent_atoms>
      </symmetry>
      <symmetry>
        <info name="120 deg rotation - cart. axis [1,-1,1]">crystal_symmetry</info>
        <rotation rank="2" dims="           3           3">
  0.000000000000000E+000  1.000000000000000E+000  0.000000000000000E+000
 -1.000000000000000E+000 -1.000000000000000E+000 -1.000000000000000E+000
  0.000000000000000E+000  0.000000000000000E+000  1.000000000000000E+000
        </rotation>
        <fractional_translation>
  0.000000000000000E+000  0.000000000000000E+000  0.000000000000000E+000
        </fractional_translation>
        <equivalent_atoms size="2" nat="2">
           1           2
        </equivalent_atoms>
      </symmetry>
      <symmetry>
        <info name="120 deg rotation - cart. axis [1,1,1]">crystal_symmetry</info>
        <rotation rank="2" dims="           3           3">
  0.000000000000000E+000  0.000000000000000E+000  1.000000000000000E+000
  0.000000000000000E+000  1.000000000000000E+000  0.000000000000000E+000
 -1.000000000000000E+000 -1.000000000000000E+000 -1.000000000000000E+000
        </rotation>
        <fractional_translation>
  0.000000000000000E+000  0.000000000000000E+000  0.000000000000000E+000
        </fractional_translation>
        <equivalent_atoms size="2" nat="2">
           1           2
        </equivalent_atoms>
      </symmetry>
      <symmetry>
        <info name="120 deg rotation - cart. axis [-1,1,-1]">crystal_symmetry</info>
        <rotation rank="2" dims="           3           3">
 -1.000000000000000E+000 -1.000000000000000E+000 -1.000000000000000E+000
  1.000000000000000E+000  0.000000000000000E+000  0.000000000000000E+000
  0.000000000000000E+000  0.000000000000000E+000  1.000000000000000E+000
        </rotation>
        <fractional_translation>
  0.000000000000000E+000  0.000000000000000E+000  0.000000000000000E+000
        </fractional_translation>
        <equivalent_atoms size="2" nat="2">
           1           2
        </equivalent_atoms>
      </symmetry>
      <symmetry>
        <info name="120 deg rotation - cart. axis [1,-1,-1]">crystal_symmetry</info>
        <rotation rank="2" dims="           3           3">
  0.000000000000000E+000  1.000000000000000E+000  0.000000000000000E+000
  0.000000000000000E+000  0.000000000000000E+000  1.000000000000000E+000
  1.000000000000000E+000  0.000000000000000E+000  0.000000000000000E+000
        </rotation>
        <fractional_translation>
  0.000000000000000E+000  0.000000000000000E+000  0.000000000000000E+000
        </fractional_translation>
        <equivalent_atoms size="2" nat="2">
           1           2
        </equivalent_atoms>
      </symmetry>
      <symmetry>
        <info name="120 deg rotation - cart. axis [-1,-1,1]">crystal_symmetry</info>
        <rotation rank="2" dims="           3           3">
  1.000000000000000E+000  0.000000000000000E+000  0.000000000000000E+000
 -1.000000000000000E+000 -1.000000000000000E+000 -1.000000000000000E+000
  0.000000000000000E+000  1.000000000000000E+000  0.000000000000000E+000
        </rotation>
        <fractional_translation>
  0.000000000000000E+000  0.000000000000000E+000  0.000000000000000E+000
        </fractional_translation>
        <equivalent_atoms size="2" nat="2">
           1           2
        </equivalent_atoms>
      </symmetry>
      <symmetry>
        <info name="inversion">crystal_symmetry</info>
        <rotation rank="2" dims="           3           3">
 -1.000000000000000E+000  0.000000000000000E+000  0.000000000000000E+000
  0.000000000000000E+000 -1.000000000000000E+000  0.000000000000000E+000
  0.000000000000000E+000  0.000000000000000E+000 -1.000000000000000E+000
        </rotation>
        <fractional_translation>
  2.500000000000000E-001  2.500000000000000E-001  2.500000000000000E-001
        </fractional_translation>
        <equivalent_atoms size="2" nat="2">
           2           1
        </equivalent_atoms>
      </symmetry>
      <symmetry>
        <info name="inv. 180 deg rotation - cart. axis [0,0,1]">crystal_symmetry</info>
        <rotation rank="2" dims="           3           3">
  0.000000000000000E+000 -1.000000000000000E+000  0.000000000000000E+000
 -1.000000000000000E+000  0.000000000000000E+000  0.000000000000000E+000
  1.000000000000000E+000  1.000000000000000E+000  1.000000000000000E+000
        </rotation>
        <fractional_translation>
  2.500000000000000E-001  2.500000000000000E-001  2.500000000000000E-001
        </fractional_translation>
        <equivalent_atoms size="2" nat="2">
           2           1
        </equivalent_atoms>
      </symmetry>
      <symmetry>
        <info name="inv. 180 deg rotation - cart. axis [0,1,0]">crystal_symmetry</info>
        <rotation rank="2" dims="           3           3">
  1.000000000000000E+000  1.000000000000000E+000  1.000000000000000E+000
  0.000000000000000E+000  0.000000000000000E+000 -1.000000000000000E+000
  0.000000000000000E+000 -1.000000000000000E+000  0.000000000000000E+000
        </rotation>
        <fractional_translation>
  2.500000000000000E-001  2.500000000000000E-001  2.500000000000000E-001
        </fractional_translation>
        <equivalent_atoms size="2" nat="2">
           2           1
        </equivalent_atoms>
      </symmetry>
      <symmetry>
        <info name="inv. 180 deg rotation - cart. axis [1,0,0]">crystal_symmetry</info>
        <rotation rank="2" dims="           3           3">
  0.000000000000000E+000  0.000000000000000E+000 -1.000000000000000E+000
  1.000000000000000E+000  1.000000000000000E+000  1.000000000000000E+000
 -1.000000000000000E+000  0.000000000000000E+000  0.000000000000000E+000
        </rotation>
        <fractional_translation>
  2.500000000000000E-001  2.500000000000000E-001  2.500000000000000E-001
        </fractional_translation>
        <equivalent_atoms size="2" nat="2">
           2           1
        </equivalent_atoms>
      </symmetry>
      <symmetry>
        <info name="inv. 180 deg rotation - cart. axis [1,1,0]">crystal_symmetry</info>
        <rotation rank="2" dims="           3           3">
  0.000000000000000E+000  1.000000000000000E+000  0.000000000000000E+000
  1.000000000000000E+000  0.000000000000000E+000  0.000000000000000E+000
  0.000000000000000E+000  0.000000000000000E+000  1.000000000000000E+000
        </rotation>
        <fractional_translation>
  0.000000000000000E+000  0.000000000000000E+000  0.000000000000000E+000
        </fractional_translation>
        <equivalent_atoms size="2" nat="2">
           1           2
        </equivalent_atoms>
      </symmetry>
      <symmetry>
        <info name="inv. 180 deg rotation - cart. axis [1,-1,0]">crystal_symmetry</info>
        <rotation rank="2" dims="           3           3">
  1.000000000000000E+000  0.000000000000000E+000  0.000000000000000E+000
  0.000000000000000E+000  1.000000000000000E+000  0.000000000000000E+000
 -1.000000000000000E+000 -1.000000000000000E+000 -1.000000000000000E+000
        </rotation>
        <fractional_translation>
  0.000000000000000E+000  0.000000000000000E+000  0.000000000000000E+000
        </fractional_translation>
        <equivalent_atoms size="2" nat="2">
           1           2
        </equivalent_atoms>
      </symmetry>
      <symmetry>
        <info name="inv.  90 deg rotation - cart. axis [0,0,-1]">crystal_symmetry</info>
        <rotation rank="2" dims="           3           3">
  0.000000000000000E+000  0.000000000000000E+000  1.000000000000000E+000
 -1.000000000000000E+000 -1.000000000000000E+000 -1.000000000000000E+000
  0.000000000000000E+000  1.000000000000000E+000  0.000000000000000E+000
        </rotation>
        <fractional_translation>
  0.000000000000000E+000  0.000000000000000E+000  0.000000000000000E+000
        </fractional_translation>
        <equivalent_atoms size="2" nat="2">
           1           2
        </equivalent_atoms>
      </symmetry>
      <symmetry>
        <info name="inv.  90 deg rotation - cart. axis [0,0,1]">crystal_symmetry</info>
        <rotation rank="2" dims="           3           3">
 -1.000000000000000E+000 -1.000000000000000E+000 -1.000000000000000E+000
  0.000000000000000E+000  0.000000000000000E+000  1.000000000000000E+000
  1.000000000000000E+000  0.000000000000000E+000  0.000000000000000E+000
        </rotation>
        <fractional_translation>
  0.000000000000000E+000  0.000000000000000E+000  0.000000000000000E+000
        </fractional_translation>
        <equivalent_atoms size="2" nat="2">
           1           2
        </equivalent_atoms>
      </symmetry>
      <symmetry>
        <info name="inv. 180 deg rotation - cart. axis [1,0,1]">crystal_symmetry</info>
        <rotation rank="2" dims="           3           3">
  1.000000000000000E+000  0.000000000000000E+000  0.000000000000000E+000
  0.000000000000000E+000  0.000000000000000E+000  1.000000000000000E+000
  0.000000000000000E+000  1.000000000000000E+000  0.000000000000000E+000
        </rotation>
        <fractional_translation>
  0.000000000000000E+000  0.000000000000000E+000  0.000000000000000E+000
        </fractional_translation>
        <equivalent_atoms size="2" nat="2">
           1           2
        </equivalent_atoms>
      </symmetry>
      <symmetry>
        <info name="inv. 180 deg rotation - cart. axis [-1,0,1]">crystal_symmetry</info>
        <rotation rank="2" dims="           3           3">
 -1.000000000000000E+000 -1.000000000000000E+000 -1.000000000000000E+000
  0.000000000000000E+000  1.000000000000000E+000  0.000000000000000E+000
  0.000000000000000E+000  0.000000000000000E+000  1.000000000000000E+000
        </rotation>
        <fractional_translation>
  0.000000000000000E+000  0.000000000000000E+000  0.000000000000000E+000
        </fractional_translation>
        <equivalent_atoms size="2" nat="2">
           1           2
        </equivalent_atoms>
      </symmetry>
      <symmetry>
        <info name="inv.  90 deg rotation - cart. axis [0,1,0]">crystal_symmetry</info>
        <rotation rank="2" dims="           3           3">
  0.000000000000000E+000  1.000000000000000E+000  0.000000000000000E+000
 -1.000000000000000E+000 -1.000000000000000E+000 -1.000000000000000E+000
  1.000000000000000E+000  0.000000000000000E+000  0.000000000000000E+000
        </rotation>
        <fractional_translation>
  0.000000000000000E+000  0.000000000000000E+000  0.000000000000000E+000
        </fractional_translation>
        <equivalent_atoms size="2" nat="2">
           1           2
        </equivalent_atoms>
      </symmetry>
      <symmetry>
        <info name="inv.  90 deg rotation - cart. axis [0,-1,0]">crystal_symmetry</info>
        <rotation rank="2" dims="           3           3">
  0.000000000000000E+000  0.000000000000000E+000  1.000000000000000E+000
  1.000000000000000E+000  0.000000000000000E+000  0.000000000000000E+000
 -1.000000000000000E+000 -1.000000000000000E+000 -1.000000000000000E+000
        </rotation>
        <fractional_translation>
  0.000000000000000E+000  0.000000000000000E+000  0.000000000000000E+000
        </fractional_translation>
        <equivalent_atoms size="2" nat="2">
           1           2
        </equivalent_atoms>
      </symmetry>
      <symmetry>
        <info name="inv. 180 deg rotation - cart. axis [0,1,1]">crystal_symmetry</info>
        <rotation rank="2" dims="           3           3">
  1.000000000000000E+000  0.000000000000000E+000  0.000000000000000E+000
 -1.000000000000000E+000 -1.000000000000000E+000 -1.000000000000000E+000
  0.000000000000000E+000  0.000000000000000E+000  1.000000000000000E+000
        </rotation>
        <fractional_translation>
  0.000000000000000E+000  0.000000000000000E+000  0.000000000000000E+000
        </fractional_translation>
        <equivalent_atoms size="2" nat="2">
           1           2
        </equivalent_atoms>
      </symmetry>
      <symmetry>
        <info name="inv. 180 deg rotation - cart. axis [0,1,-1]">crystal_symmetry</info>
        <rotation rank="2" dims="           3           3">
  0.000000000000000E+000  0.000000000000000E+000  1.000000000000000E+000
  0.000000000000000E+000  1.000000000000000E+000  0.000000000000000E+000
  1.000000000000000E+000  0.000000000000000E+000  0.000000000000000E+000
        </rotation>
        <fractional_translation>
  0.000000000000000E+000  0.000000000000000E+000  0.000000000000000E+000
        </fractional_translation>
        <equivalent_atoms size="2" nat="2">
           1           2
        </equivalent_atoms>
      </symmetry>
      <symmetry>
        <info name="inv.  90 deg rotation - cart. axis [-1,0,0]">crystal_symmetry</info>
        <rotation rank="2" dims="           3           3">
  0.000000000000000E+000  1.000000000000000E+000  0.000000000000000E+000
  0.000000000000000E+000  0.000000000000000E+000  1.000000000000000E+000
 -1.000000000000000E+000 -1.000000000000000E+000 -1.000000000000000E+000
        </rotation>
        <fractional_translation>
  0.000000000000000E+000  0.000000000000000E+000  0.000000000000000E+000
        </fractional_translation>
        <equivalent_atoms size="2" nat="2">
           1           2
        </equivalent_atoms>
      </symmetry>
      <symmetry>
        <info name="inv.  90 deg rotation - cart. axis [1,0,0]">crystal_symmetry</info>
        <rotation rank="2" dims="           3           3">
 -1.000000000000000E+000 -1.000000000000000E+000 -1.000000000000000E+000
  1.000000000000000E+000  0.000000000000000E+000  0.000000000000000E+000
  0.000000000000000E+000  1.000000000000000E+000  0.000000000000000E+000
        </rotation>
        <fractional_translation>
  0.000000000000000E+000  0.000000000000000E+000  0.000000000000000E+000
        </fractional_translation>
        <equivalent_atoms size="2" nat="2">
           1           2
        </equivalent_atoms>
      </symmetry>
      <symmetry>
        <info name="inv. 120 deg rotation - cart. axis [-1,-1,-1]">crystal_symmetry</info>
        <rotation rank="2" dims="           3           3">
  1.000000000000000E+000  1.000000000000000E+000  1.000000000000000E+000
  0.000000000000000E+000 -1.000000000000000E+000  0.000000000000000E+000
 -1.000000000000000E+000  0.000000000000000E+000  0.000000000000000E+000
        </rotation>
        <fractional_translation>
  2.500000000000000E-001  2.500000000000000E-001  2.500000000000000E-001
        </fractional_translation>
        <equivalent_atoms size="2" nat="2">
           2           1
        </equivalent_atoms>
      </symmetry>
      <symmetry>
        <info name="inv. 120 deg rotation - cart. axis [-1,1,1]">crystal_symmetry</info>
        <rotation rank="2" dims="           3           3">
  0.000000000000000E+000  0.000000000000000E+000 -1.000000000000000E+000
 -1.000000000000000E+000  0.000000000000000E+000  0.000000000000000E+000
  0.000000000000000E+000 -1.000000000000000E+000  0.000000000000000E+000
        </rotation>
        <fractional_translation>
  2.500000000000000E-001  2.500000000000000E-001  2.500000000000000E-001
        </fractional_translation>
        <equivalent_atoms size="2" nat="2">
           2           1
        </equivalent_atoms>
      </symmetry>
      <symmetry>
        <info name="inv. 120 deg rotation - cart. axis [1,1,-1]">crystal_symmetry</info>
        <rotation rank="2" dims="           3           3">
 -1.000000000000000E+000  0.000000000000000E+000  0.000000000000000E+000
  0.000000000000000E+000  0.000000000000000E+000 -1.000000000000000E+000
  1.000000000000000E+000  1.000000000000000E+000  1.000000000000000E+000
        </rotation>
        <fractional_translation>
  2.500000000000000E-001  2.500000000000000E-001  2.500000000000000E-001
        </fractional_translation>
        <equivalent_atoms size="2" nat="2">
           2           1
        </equivalent_atoms>
      </symmetry>
      <symmetry>
        <info name="inv. 120 deg rotation - cart. axis [1,-1,1]">crystal_symmetry</info>
        <rotation rank="2" dims="           3           3">
  0.000000000000000E+000 -1.000000000000000E+000  0.000000000000000E+000
  1.000000000000000E+000  1.000000000000000E+000  1.000000000000000E+000
  0.000000000000000E+000  0.000000000000000E+000 -1.000000000000000E+000
        </rotation>
        <fractional_translation>
  2.500000000000000E-001  2.500000000000000E-001  2.500000000000000E-001
        </fractional_translation>
        <equivalent_atoms size="2" nat="2">
           2           1
        </equivalent_atoms>
      </symmetry>
      <symmetry>
        <info name="inv. 120 deg rotation - cart. axis [1,1,1]">crystal_symmetry</info>
        <rotation rank="2" dims="           3           3">
  0.000000000000000E+000  0.000000000000000E+000 -1.000000000000000E+000
  0.000000000000000E+000 -1.000000000000000E+000  0.000000000000000E+000
  1.000000000000000E+000  1.000000000000000E+000  1.000000000000000E+000
        </rotation>
        <fractional_translation>
  2.500000000000000E-001  2.500000000000000E-001  2.500000000000000E-001
        </fractional_translation>
        <equivalent_atoms size="2" nat="2">
           2           1
        </equivalent_atoms>
      </symmetry>
      <symmetry>
        <info name="inv. 120 deg rotation - cart. axis [-1,1,-1]">crystal_symmetry</info>
        <rotation rank="2" dims="           3           3">
  1.000000000000000E+000  1.000000000000000E+000  1.000000000000000E+000
 -1.000000000000000E+000  0.000000000000000E+000  0.000000000000000E+000
  0.000000000000000E+000  0.000000000000000E+000 -1.000000000000000E+000
        </rotation>
        <fractional_translation>
  2.500000000000000E-001  2.500000000000000E-001  2.500000000000000E-001
        </fractional_translation>
        <equivalent_atoms size="2" nat="2">
           2           1
        </equivalent_atoms>
      </symmetry>
      <symmetry>
        <info name="inv. 120 deg rotation - cart. axis [1,-1,-1]">crystal_symmetry</info>
        <rotation rank="2" dims="           3           3">
  0.000000000000000E+000 -1.000000000000000E+000  0.000000000000000E+000
  0.000000000000000E+000  0.000000000000000E+000 -1.000000000000000E+000
 -1.000000000000000E+000  0.000000000000000E+000  0.000000000000000E+000
        </rotation>
        <fractional_translation>
  2.500000000000000E-001  2.500000000000000E-001  2.500000000000000E-001
        </fractional_translation>
        <equivalent_atoms size="2" nat="2">
           2           1
        </equivalent_atoms>
      </symmetry>
      <symmetry>
        <info name="inv. 120 deg rotation - cart. axis [-1,-1,1]">crystal_symmetry</info>
        <rotation rank="2" dims="           3           3">
 -1.000000000000000E+000  0.000000000000000E+000  0.000000000000000E+000
  1.000000000000000E+000  1.000000000000000E+000  1.000000000000000E+000
  0.000000000000000E+000 -1.000000000000000E+000  0.000000000000000E+000
        </rotation>
        <fractional_translation>
  2.500000000000000E-001  2.500000000000000E-001  2.500000000000000E-001
        </fractional_translation>
        <equivalent_atoms size="2" nat="2">
           2           1
        </equivalent_atoms>
      </symmetry>
    </symmetries>
    <basis_set>
      <gamma_only>false</gamma_only>
      <ecutwfc>3.000000000000000E+001</ecutwfc>
      <ecutrho>1.200000000000000E+002</ecutrho>
      <fft_grid nr1="36" nr2="36" nr3="36"></fft_grid>
      <fft_smooth nr1="36" nr2="36" nr3="36"></fft_smooth>
      <fft_box nr1="36" nr2="36" nr3="36"></fft_box>
      <ngm>16625</ngm>
      <ngms>16625</ngms>
      <npwx>2100</npwx>
      <reciprocal_lattice>
        <b1>
 -1.001205436898062E+000 -1.001205436898062E+000  1.001205436898062E+000
        </b1>
        <b2>1.001205436898062E+000  1.001205436898062E+000  1.001205436898062E+000</b2>
        <b3>-1.001205436898062E+000  1.001205436898062E+000 -1.001205436898062E+000</b3>
      </reciprocal_lattice>
    </basis_set>
    <dft>
      <functional>PW</functional>
    </dft>
    <magnetization>
      <lsda>false</lsda>
      <noncolin>false</noncolin>
      <spinorbit>false</spinorbit>
      <absolute>0.000000000000000E+000</absolute>
    </magnetization>
    <total_energy>
      <etot>-8.524491676616609E+000</etot>
      <eband>3.284784221724633E-001</eband>
      <ehart>5.418123665719099E-001</ehart>
      <vtxc>-3.251404231883971E+000</vtxc>
      <etxc>-3.110753170885694E+000</etxc>
      <ewald>-8.451779025093533E+000</ewald>
    </total_energy>
    <band_structure>
      <lsda>false</lsda>
      <noncolin>false</noncolin>
      <spinorbit>false</spinorbit>
      <nbnd>8</nbnd>
      <nelec>8.000000000000000E+000</nelec>
      <num_of_atomic_wfc>8</num_of_atomic_wfc>
      <wf_collected>true</wf_collected>
      <fermi_energy>2.415802883531201E-001</fermi_energy>
      <starting_k_points>
        <monkhorst_pack nk1="6" nk2="6" nk3="6" k1="0" k2="0" k3="0">Monkhorst-Pack</monkhorst_pack>
      </starting_k_points>
      <nks>16</nks>
      <occupations_kind>tetrahedra_opt</occupations_kind>
      <ks_energies>
        <k_point weight="9.2592592592592587E-003">0.000000000000000E+000  0.000000000000000E+000  0.000000000000000E+000</k_point>
        <npw>2085</npw>
        <eigenvalues size="8">
 -2.150085553149673E-001  2.293991067571482E-001  2.293991067592746E-001
  2.293991068531031E-001  3.227242640112215E-001
  3.227242654632951E-001  3.227242662583442E-001  3.537752899627081E-001
        </eigenvalues>
        <occupations size="8">
  9.999999999999983E-001  9.996318082308064E-001  9.996318082308064E-001
  9.996318082308064E-001  0.000000000000000E+000
  0.000000000000000E+000  0.000000000000000E+000  0.000000000000000E+000
        </occupations>
      </ks_energies>
      <ks_energies>
        <k_point weight="7.4074074074074070E-002">
 -1.668675728163437E-001  1.668675728163437E-001 -1.668675728163437E-001
        </k_point>
        <npw>2070</npw>
        <eigenvalues size="8">
 -2.015222981384627E-001  1.406668748075811E-001  2.125453837309932E-001
  2.125453837333381E-001  3.145286349348533E-001
  3.468464410492367E-001  3.468464440990888E-001  4.299903039553048E-001
        </eigenvalues>
        <occupations size="8">
  9.999999999999919E-001  1.000006397630170E+000  9.999999999999919E-001
  9.999999999999919E-001  0.000000000000000E+000
  0.000000000000000E+000  0.000000000000000E+000  0.000000000000000E+000
        </occupations>
      </ks_energies>
      <ks_energies>
        <k_point weight="7.4074074074074070E-002">
 -3.337351456326874E-001  3.337351456326874E-001 -3.337351456326874E-001
        </k_point>
        <npw>2090</npw>
        <eigenvalues size="8">
 -1.635124940940992E-001  3.054645198072900E-002  1.921523176281731E-001
  1.921523176441472E-001  2.924216596887421E-001
  3.571696789447039E-001  3.571696823412375E-001  5.143422505356875E-001
        </eigenvalues>
        <occupations size="8">
  9.999999999999938E-001  1.000005405552788E+000  9.999999999999938E-001
  9.999999999999938E-001  0.000000000000000E+000
  0.000000000000000E+000  0.000000000000000E+000  0.000000000000000E+000
        </occupations>
      </ks_energies>
      <ks_energies>
        <k_point weight="3.7037037037037035E-002">
  5.006027184490311E-001 -5.006027184490311E-001  5.006027184490311E-001
        </k_point>
        <npw>2060</npw>
        <eigenvalues size="8">
 -1.274202052760458E-001 -3.087859131143576E-002  1.848426946292983E-001
  1.848426946293137E-001  2.840350165862994E-001
  3.505885265177375E-001  3.505885265280645E-001  5.070549814159925E-001
        </eigenvalues>
        <occupations size="8">
  9.999999999999989E-001  9.999999999999989E-001  9.999999999999989E-001
  9.999999999999989E-001  0.000000000000000E+000
  0.000000000000000E+000  0.000000000000000E+000  0.000000000000000E+000
        </occupations>
      </ks_energies>
      <ks_energies>
        <k_point weight="5.5555555555555552E-002">
  0.000000000000000E+000  3.337351456326874E-001  0.000000000000000E+000
        </k_point>
        <npw>2061</npw>
        <eigenvalues size="8">
 -1.969391409893046E-001  1.542576567144065E-001  1.846055085692611E-001
  1.846055085704898E-001  2.893790113727823E-001
  3.861716239802885E-001  3.891405181447623E-001  3.891405234481214E-001
        </eigenvalues>
        <occupations size="8">
  9.999999999999947E-001  9.999985493404613E-001  9.999999999999947E-001
  9.999999999999947E-001  0.000000000000000E+000
 -2.405290871294906E-006  0.000000000000000E+000  0.000000000000000E+000
        </occupations>
      </ks_energies>
      <ks_energies>
        <k_point weight="0.22222222222222221">
 -1.668675728163437E-001  5.006027184490311E-001 -1.668675728163437E-001
        </k_point>
        <npw>2078</npw>
        <eigenvalues size="8">
 -1.664706195499580E-001  6.468669231375375E-002  1.546245345524753E-001
  1.640333455050843E-001  2.988444434866639E-001
  3.773961976269222E-001  3.943087455068235E-001  4.158289517894047E-001
        </eigenvalues>
        <occupations size="8">
  1.000000000000001E+000  9.999984965210919E-001  1.000000000000001E+000
  1.000000000000001E+000  0.000000000000000E+000
  6.073778028717647E-007  0.000000000000000E+000  0.000000000000000E+000
        </occupations>
      </ks_energies>
      <ks_energies>
        <k_point weight="0.22222222222222221">
  6.674702912653748E-001 -3.337351456326875E-001  6.674702912653748E-001
        </k_point>
        <npw>2078</npw>
        <eigenvalues size="8">
 -1.216449979352076E-001 -1.668972758122606E-002  1.252671377993124E-001
  1.630416748792256E-001  3.014886834728370E-001
  3.794697782584115E-001  3.985121594181403E-001  4.642703857734946E-001
        </eigenvalues>
        <occupations size="8">
  1.000000000000001E+000  1.000000000000001E+000  1.000000000000001E+000
  1.000000000000001E+000  0.000000000000000E+000
 -1.823508457087502E-006  0.000000000000000E+000  0.000000000000000E+000
        </occupations>
      </ks_energies>
      <ks_energies>
        <k_point weight="0.22222222222222221">
  5.006027184490311E-001 -1.668675728163438E-001  5.006027184490311E-001
        </k_point>
        <npw>2082</npw>
        <eigenvalues size="8">
 -1.361837254373018E-001  5.863320476606297E-003  1.149516504468144E-001
  1.810462527368977E-001  3.173777219816407E-001
  3.792079177031960E-001  3.840295736091467E-001  4.961351992908045E-001
        </eigenvalues>
        <occupations size="8">
  1.000000000000001E+000  1.000000000000001E+000  1.000000000000001E+000
  1.000000000000001E+000  0.000000000000000E+000
  0.000000000000000E+000  0.000000000000000E+000  0.000000000000000E+000
        </occupations>
      </ks_energies>
      <ks_energies>
        <k_point weight="0.11111111111111110">
  3.337351456326874E-001  0.000000000000000E+000  3.337351456326874E-001
        </k_point>
        <npw>2083</npw>
        <eigenvalues size="8">
 -1.795437874528497E-001  9.155404926869232E-002  1.383587487284115E-001
  2.084753492165703E-001  3.404859039016048E-001
  3.596314792723263E-001  3.692388083510669E-001  4.361923184810184E-001
        </eigenvalues>
        <occupations size="8">
  9.999999999999971E-001  1.000000386176408E+000  9.999999999999971E-001
  9.999999999999971E-001  0.000000000000000E+000
  0.000000000000000E+000  0.000000000000000E+000  0.000000000000000E+000
        </occupations>
      </ks_energies>
      <ks_energies>
        <k_point weight="5.5555555555555552E-002">
  0.000000000000000E+000  6.674702912653748E-001  0.000000000000000E+000
        </k_point>
        <npw>2080</npw>
        <eigenvalues size="8">
 -1.439277891708652E-001  4.417024326926043E-002  1.389360364674535E-001
  1.389360364772175E-001  2.518909456628284E-001
  2.982605883358461E-001  4.968971273134180E-001  4.968971439454567E-001
        </eigenvalues>
        <occupations size="8">
  9.999999999999942E-001  1.000005975782755E+000  9.999999999999942E-001
  9.999999999999942E-001  0.000000000000000E+000
  2.765148104547281E-007  0.000000000000000E+000  0.000000000000000E+000
        </occupations>
      </ks_energies>
      <ks_energies>
        <k_point weight="0.22222222222222221">
  8.343378640817187E-001 -1.668675728163438E-001  8.343378640817187E-001
        </k_point>
        <npw>2074</npw>
        <eigenvalues size="8">
 -1.003641911296494E-001 -1.367404560826659E-002  9.254602418397284E-002
  1.338895910093278E-001  2.640693445463175E-001
  3.261883972330836E-001  5.036209524470709E-001  5.044651469544634E-001
        </eigenvalues>
        <occupations size="8">
  1.000000000000001E+000  1.000000000000001E+000  1.000000000000001E+000
  1.000000000000001E+000  0.000000000000000E+000
 -2.620442913162531E-006  0.000000000000000E+000  0.000000000000000E+000
        </occupations>
      </ks_energies>
      <ks_energies>
        <k_point weight="0.11111111111111110">
  6.674702912653749E-001  0.000000000000000E+000  6.674702912653749E-001
        </k_point>
        <npw>2079</npw>
        <eigenvalues size="8">
 -9.274628115593098E-002 -2.155558501307429E-002  6.289588154473125E-002
  1.504719253827842E-001  2.830944192837718E-001
  4.404104262093800E-001  4.677813737600285E-001  4.895026842735437E-001
        </eigenvalues>
        <occupations size="8">
  9.999999999999981E-001  9.999999999999981E-001  9.999999999999981E-001
  9.999999999999981E-001  0.000000000000000E+000
 -1.267052950907691E-007  0.000000000000000E+000  0.000000000000000E+000
        </occupations>
      </ks_energies>
      <ks_energies>
        <k_point weight="2.7777777777777776E-002">
  0.000000000000000E+000 -1.001205436898062E+000  0.000000000000000E+000
        </k_point>
        <npw>2100</npw>
        <eigenvalues size="8">
 -6.032643083565439E-002 -6.032643082596714E-002  1.227481864068044E-001
  1.227481865035028E-001  2.506341145030951E-001
  2.506341145564199E-001  6.016407402715083E-001  6.016408522978240E-001
        </eigenvalues>
        <occupations size="8">
  9.999999999999979E-001  9.999999999999979E-001  9.999999999999979E-001
  9.999999999999979E-001  1.867302982007752E-004
  1.867302982007752E-004  0.000000000000000E+000  0.000000000000000E+000
        </occupations>
      </ks_energies>
      <ks_energies>
        <k_point weight="0.22222222222222221">
  6.674702912653747E-001 -3.337351456326875E-001  1.001205436898062E+000
        </k_point>
        <npw>2092</npw>
        <eigenvalues size="8">
 -1.294323879631277E-001  2.047419005042211E-002  9.489800936452339E-002
  1.430884186697642E-001  3.320124213246805E-001
  3.627396166049615E-001  3.844263058375644E-001  4.892921611284606E-001
        </eigenvalues>
        <occupations size="8">
  1.000000000000002E+000  1.000000000000002E+000  1.000000000000002E+000
  1.000000000000002E+000  0.000000000000000E+000
 -1.128168777986622E-007  0.000000000000000E+000  0.000000000000000E+000
        </occupations>
      </ks_energies>
      <ks_energies>
        <k_point weight="0.22222222222222221">
  5.006027184490311E-001 -1.668675728163438E-001  8.343378640817186E-001
        </k_point>
        <npw>2088</npw>
        <eigenvalues size="8">
 -9.233899839525536E-002 -2.453598172317502E-002  7.844833701836273E-002
  1.253855253829162E-001  3.497137561646426E-001
  3.587309253557573E-001  4.521380209155252E-001  4.687232269443514E-001
        </eigenvalues>
        <occupations size="8">
  1.000000000000002E+000  1.000000000000002E+000  1.000000000000002E+000
  1.000000000000002E+000  0.000000000000000E+000
  9.664481523187406E-007  0.000000000000000E+000  0.000000000000000E+000
        </occupations>
      </ks_energies>
      <ks_energies>
        <k_point weight="0.11111111111111110">
 -3.337351456326874E-001 -1.001205436898062E+000  0.000000000000000E+000
        </k_point>
        <npw>2090</npw>
        <eigenvalues size="8">
 -5.562472599574343E-002 -5.562472599434003E-002  9.200747979114510E-002
  9.200747979297635E-002  3.274848058389675E-001
  3.274848058849154E-001  4.776125949217427E-001  4.776125965983386E-001
        </eigenvalues>
        <occupations size="8">
  9.999999999999988E-001  9.999999999999988E-001  9.999999999999988E-001
  9.999999999999988E-001 -8.355479485532483E-007
 -8.355479485532483E-007  0.000000000000000E+000  0.000000000000000E+000
        </occupations>
      </ks_energies>
    </band_structure>
    <forces rank="2" dims="           3           2">
  0.000000000000000E+000  0.000000000000000E+000  0.000000000000000E+000
  0.000000000000000E+000  0.000000000000000E+000  0.000000000000000E+000
    </forces>
    <stress rank="2" dims="           3           3">
 -1.645225768743173E-006  1.058791184067875E-022 -7.411538288475128E-022
  1.058791184067875E-022 -1.645225768743173E-006  1.058791184067875E-022
 -7.411538288475128E-022  3.176373552203626E-022 -1.645225768743172E-006
    </stress>
  </output>
  <exit_status>0</exit_status>
  <timing_info>
    <total label="PWSCF">
      <cpu>1.531137100000000E+001</cpu>
      <wall>1.554465413093567E+001</wall>
    </total>
    <partial label="init_run" calls="2">
      <cpu>1.115318000000000E+000</cpu>
      <wall>1.168157100677490E+000</wall>
    </partial>
    <partial label="hinit0" calls="2">
      <cpu>4.966699999999999E-001</cpu>
      <wall>5.330066680908203E-001</wall>
    </partial>
    <partial label="init_vloc" calls="4">
      <cpu>5.415300000000123E-002</cpu>
      <wall>5.472278594970703E-002</wall>
    </partial>
    <partial label="init_us_1" calls="2">
      <cpu>5.031699999999795E-002</cpu>
      <wall>5.031895637512207E-002</wall>
    </partial>
    <partial label="fft" calls="84">
      <cpu>2.250419999999966E-001</cpu>
      <wall>2.474663257598877E-001</wall>
    </partial>
    <partial label="potinit" calls="2">
      <cpu>9.806500000000007E-002</cpu>
      <wall>9.908080101013184E-002</wall>
    </partial>
    <partial label="v_of_rho" calls="17">
      <cpu>7.948699999999853E-002</cpu>
      <wall>7.991456985473633E-002</wall>
    </partial>
    <partial label="v_xc" calls="25">
      <cpu>9.494800000000225E-002</cpu>
      <wall>9.542942047119141E-002</wall>
    </partial>
    <partial label="v_h" calls="17">
      <cpu>1.374999999999993E-002</cpu>
      <wall>1.376199722290039E-002</wall>
    </partial>
    <partial label="wfcinit" calls="2">
      <cpu>4.932759999999998E-001</cpu>
      <wall>4.977419376373291E-001</wall>
    </partial>
    <partial label="init_us_2" calls="672">
      <cpu>4.278869999999682E-001</cpu>
      <wall>4.291250705718994E-001</wall>
    </partial>
    <partial label="init_us_2:cp" calls="672">
      <cpu>4.246209999999948E-001</cpu>
      <wall>4.271481037139893E-001</wall>
    </partial>
    <partial label="wfcinit:atom" calls="32">
      <cpu>1.046800000000125E-002</cpu>
      <wall>1.046919822692871E-002</wall>
    </partial>
    <partial label="atomic_wfc" calls="32">
      <cpu>1.032999999999795E-002</cpu>
      <wall>1.035737991333008E-002</wall>
    </partial>
    <partial label="wfcinit:wfcr" calls="32">
      <cpu>4.308600000000027E-001</cpu>
      <wall>4.348001480102539E-001</wall>
    </partial>
    <partial label="wfcrot" calls="32">
      <cpu>4.307279999999967E-001</cpu>
      <wall>4.346969127655029E-001</wall>
    </partial>
    <partial label="rotwfck" calls="32">
      <cpu>4.302310000000009E-001</cpu>
      <wall>4.335749149322510E-001</wall>
    </partial>
    <partial label="rotwfck:hpsi" calls="32">
      <cpu>3.986500000000035E-001</cpu>
      <wall>4.006128311157227E-001</wall>
    </partial>
    <partial label="h_psi_bgrp" calls="1105">
      <cpu>7.339281999999949E+000</cpu>
      <wall>7.404601812362671E+000</wall>
    </partial>
    <partial label="h_psi" calls="1105">
      <cpu>7.336473000000023E+000</cpu>
      <wall>7.402020931243896E+000</wall>
    </partial>
    <partial label="h_psi:pot" calls="1105">
      <cpu>7.303908999999999E+000</cpu>
      <wall>7.368948936462402E+000</wall>
    </partial>
    <partial label="vloc_psi" calls="1105">
      <cpu>5.491933999999997E+000</cpu>
      <wall>5.540062189102173E+000</wall>
    </partial>
    <partial label="fftw" calls="14902">
      <cpu>5.287618000000021E+000</cpu>
      <wall>5.337761878967285E+000</wall>
    </partial>
    <partial label="h_psi:calbec" calls="1105">
      <cpu>9.840459999999638E-001</cpu>
      <wall>9.930562973022461E-001</wall>
    </partial>
    <partial label="calbec" calls="1425">
      <cpu>1.505614999999974E+000</cpu>
      <wall>1.516315937042236E+000</wall>
    </partial>
    <partial label="add_vuspsi" calls="1105">
      <cpu>8.102650000000047E-001</cpu>
      <wall>8.193435668945312E-001</wall>
    </partial>
    <partial label="rotwfck:hc" calls="32">
      <cpu>2.207700000000123E-002</cpu>
      <wall>2.213144302368164E-002</wall>
    </partial>
    <partial label="rotwfck:diag" calls="32">
      <cpu>1.602000000003656E-003</cpu>
      <wall>2.971410751342773E-003</wall>
    </partial>
    <partial label="cdiaghg" calls="993">
      <cpu>8.842500000000975E-002</cpu>
      <wall>9.120702743530273E-002</wall>
    </partial>
    <partial label="rotwfck:evc" calls="32">
      <cpu>7.606999999998365E-003</cpu>
      <wall>7.631778717041016E-003</wall>
    </partial>
    <partial label="electrons" calls="4">
      <cpu>1.122865200000000E+001</cpu>
      <wall>1.134322500228882E+001</wall>
    </partial>
    <partial label="c_bands" calls="16">
      <cpu>9.418802999999995E+000</cpu>
      <wall>9.512812137603760E+000</wall>
    </partial>
    <partial label="cegterg" calls="256">
      <cpu>8.384149000000019E+000</cpu>
      <wall>8.467010259628296E+000</wall>
    </partial>
    <partial label="cegterg:init" calls="256">
      <cpu>1.258950000000016E-001</cpu>
      <wall>1.279227733612061E-001</wall>
    </partial>
    <partial label="cegterg:upda" calls="817">
      <cpu>2.265739999999692E-001</cpu>
      <wall>2.326464653015137E-001</wall>
    </partial>
    <partial label="g_psi" calls="817">
      <cpu>3.920399999998914E-002</cpu>
      <wall>3.973484039306641E-002</wall>
    </partial>
    <partial label="cegterg:over" calls="817">
      <cpu>4.641749999999849E-001</cpu>
      <wall>4.700915813446045E-001</wall>
    </partial>
    <partial label="cegterg:diag" calls="961">
      <cpu>8.983199999998526E-002</cpu>
      <wall>9.097075462341309E-002</wall>
    </partial>
    <partial label="cegterg:last" calls="608">
      <cpu>4.260319999999904E-001</cpu>
      <wall>4.281883239746094E-001</wall>
    </partial>
    <partial label="sum_band" calls="16">
      <cpu>1.696628000000000E+000</cpu>
      <wall>1.706672430038452E+000</wall>
    </partial>
    <partial label="sum_band:wei" calls="16">
      <cpu>5.984789999999993E-001</cpu>
      <wall>5.985345840454102E-001</wall>
    </partial>
    <partial label="sum_band:loo" calls="16">
      <cpu>1.028339000000001E+000</cpu>
      <wall>1.038375616073608E+000</wall>
    </partial>
    <partial label="sum_band:buf" calls="256">
      <cpu>1.195799999999103E-002</cpu>
      <wall>1.196956634521484E-002</wall>
    </partial>
    <partial label="sum_band:ini" calls="256">
      <cpu>1.406329999999940E-001</cpu>
      <wall>1.406641006469727E-001</wall>
    </partial>
    <partial label="ffts" calls="16">
      <cpu>8.823999999997056E-003</cpu>
      <wall>8.836746215820312E-003</wall>
    </partial>
    <partial label="sum_band:sym" calls="16">
      <cpu>5.798900000000096E-002</cpu>
      <wall>5.799102783203125E-002</wall>
    </partial>
    <partial label="mix_rho" calls="16">
      <cpu>2.347099999999713E-002</cpu>
      <wall>2.347517013549805E-002</wall>
    </partial>
    <partial label="high_freq_mi" calls="9">
      <cpu>4.589999999993211E-004</cpu>
      <wall>4.420280456542969E-004</wall>
    </partial>
    <partial label="ions" calls="4">
      <cpu>2.867356000000001E+000</cpu>
      <wall>2.904175043106079E+000</wall>
    </partial>
    <partial label="forces" calls="4">
      <cpu>5.927439999999979E-001</cpu>
      <wall>5.956990718841553E-001</wall>
    </partial>
    <partial label="frc_us" calls="4">
      <cpu>5.571520000000003E-001</cpu>
      <wall>5.580389499664307E-001</wall>
    </partial>
    <partial label="frc_lc" calls="4">
      <cpu>6.577000000000055E-003</cpu>
      <wall>6.580114364624023E-003</wall>
    </partial>
    <partial label="frc_cc" calls="4">
      <cpu>1.914999999999978E-002</cpu>
      <wall>2.122879028320312E-002</wall>
    </partial>
    <partial label="frc_scc" calls="4">
      <cpu>7.037000000000404E-003</cpu>
      <wall>7.040262222290039E-003</wall>
    </partial>
    <partial label="stress" calls="4">
      <cpu>2.252520000000002E+000</cpu>
      <wall>2.273207902908325E+000</wall>
    </partial>
    <partial label="update_pot" calls="2">
      <cpu>1.796899999999990E-002</cpu>
      <wall>1.805591583251953E-002</wall>
    </partial>
  </timing_info>
  <closed DATE="15 Dec 2024" TIME="21:52:13"></closed>
</qes:espresso>
